layout_display/__init__.py
layout_display/layout_display.py
layout_display/layout_display_ui.py
layout_display/layout_graphics.py
layout_display/resources_rc.py
layout_display/steno_layout.py
plover_layout_display-0.1.2.dist-info/METADATA
plover_layout_display-0.1.2.dist-info/WHEEL
plover_layout_display-0.1.2.dist-info/entry_points.txt
plover_layout_display-0.1.2.dist-info/top_level.txt
plover_layout_display-0.1.2.dist-info/zip-safe
plover_layout_display-0.1.2.dist-info/RECORD
